onion_config/__init__.py
onion_config/__version__.py
onion_config/_base.py
onion_config/_consts.py
onion_config/_schemas.py
onion_config/_utils.py
onion_config-5.1.1.dist-info/LICENCE.txt
onion_config-5.1.1.dist-info/METADATA
onion_config-5.1.1.dist-info/WHEEL
onion_config-5.1.1.dist-info/top_level.txt
onion_config-5.1.1.dist-info/RECORD
