Metadata-Version: 2.2
Name: onion_config
Version: 5.1.1
Summary: `onion_config` is a Python package designed for easy configuration management. It supports loading and validating configuration data from environment variables and configuration files in JSON and YAML formats. It is a `Pydantic` based custom configuration package for Python projects.
Author-email: Batkhuu Byambajav <batkhuu10@gmail.com>
Project-URL: Homepage, https://github.com/bybatkhuu/module.python-config
Project-URL: Documentation, https://bybatkhuu.github.io/module.python-config
Project-URL: Repository, https://github.com/bybatkhuu/module.python-config.git
Project-URL: Issues, https://github.com/bybatkhuu/module.python-config/issues
Project-URL: Changelog, https://github.com/bybatkhuu/module.python-config/CHANGELOG.md
Keywords: onion_config,config,configs,dotenv,python-dotenv,pydantic,pydantic-config,pydantic-settings,custom-config
Classifier: Development Status :: 4 - Beta
Classifier: Intended Audience :: Developers
Classifier: Topic :: Software Development :: Libraries
Classifier: License :: OSI Approved :: MIT License
Classifier: Operating System :: OS Independent
Classifier: Programming Language :: Python :: 3
Classifier: Programming Language :: Python :: 3.9
Classifier: Programming Language :: Python :: 3.10
Classifier: Programming Language :: Python :: 3.11
Classifier: Programming Language :: Python :: 3.12
Classifier: Programming Language :: Python :: 3.13
Requires-Python: <4.0,>=3.9
License-File: LICENCE.txt
Requires-Dist: python-dotenv<2.0.0,>=1.0.1
Requires-Dist: PyYAML<7.0,>=6.0.1
Requires-Dist: loguru<1.0.0,>=0.7.2
Requires-Dist: pydantic[email]!=2.0.0,!=2.0.1,!=2.1.0,<3.0.0,>=1.10.14
Provides-Extra: pydantic-v1
Requires-Dist: pydantic[dotenv,email]<2.0.0,>=1.10.14; extra == "pydantic-v1"
Provides-Extra: pydantic-settings
Requires-Dist: pydantic[email,timezone]!=2.0.1,!=2.1.0,<3.0.0,>2.0.0; extra == "pydantic-settings"
Requires-Dist: pydantic-settings<3.0.0,>=2.1.0; extra == "pydantic-settings"
